odoo/addons/ssi_field_service/README.rst
odoo/addons/ssi_field_service/__init__.py
odoo/addons/ssi_field_service/__manifest__.py
odoo/addons/ssi_field_service/menu.xml
odoo/addons/ssi_field_service/data/approval_template_data.xml
odoo/addons/ssi_field_service/data/base_automation_data.xml
odoo/addons/ssi_field_service/data/ir_actions_server_data.xml
odoo/addons/ssi_field_service/data/ir_sequence_data.xml
odoo/addons/ssi_field_service/data/policy_template_data.xml
odoo/addons/ssi_field_service/data/sequence_template_data.xml
odoo/addons/ssi_field_service/demo/field_service_role_demo.xml
odoo/addons/ssi_field_service/demo/field_service_role_set_demo.xml
odoo/addons/ssi_field_service/demo/field_service_time_slot_demo.xml
odoo/addons/ssi_field_service/demo/field_service_type_demo.xml
odoo/addons/ssi_field_service/models/__init__.py
odoo/addons/ssi_field_service/models/field_service_order.py
odoo/addons/ssi_field_service/models/field_service_order_role.py
odoo/addons/ssi_field_service/models/field_service_role.py
odoo/addons/ssi_field_service/models/field_service_role_set.py
odoo/addons/ssi_field_service/models/field_service_role_set_team.py
odoo/addons/ssi_field_service/models/field_service_time_slot.py
odoo/addons/ssi_field_service/models/field_service_type.py
odoo/addons/ssi_field_service/models/field_service_type_role.py
odoo/addons/ssi_field_service/models/group_field_service_order.py
odoo/addons/ssi_field_service/models/group_field_service_order_recurring_pattern.py
odoo/addons/ssi_field_service/security/ir.model.access.csv
odoo/addons/ssi_field_service/security/ir_module_category_data.xml
odoo/addons/ssi_field_service/security/ir_rule_data.xml
odoo/addons/ssi_field_service/security/res_group_data.xml
odoo/addons/ssi_field_service/static/description/icon.png
odoo/addons/ssi_field_service/static/description/risk-assessment-template.odt
odoo/addons/ssi_field_service/views/field_service_order_views.xml
odoo14_addon_ssi_field_service-14.0.1.0.1.dev2.dist-info/METADATA
odoo14_addon_ssi_field_service-14.0.1.0.1.dev2.dist-info/WHEEL
odoo14_addon_ssi_field_service-14.0.1.0.1.dev2.dist-info/top_level.txt
odoo14_addon_ssi_field_service-14.0.1.0.1.dev2.dist-info/RECORD
